{
  "resourceType": "Bundle",
  "type": "transaction",
  "entry": [
    {
      "fullUrl": "urn:uuid:57e6cb1e-9930-5520-8c92-845afe5b38e3",
      "resource": {
        "resourceType": "Patient",
        "id": "GPX-SYN-0000000132-1",
        "meta": {
          "profile": [
            "http://hl7.org/fhir/us/core/StructureDefinition/us-core-patient|6.1.0"
          ],
          "tag": [
            {
              "system": "http://terminology.hl7.org/CodeSystem/v3-ActReason",
              "code": "HTEST",
              "display": "test health data"
            }
          ]
        },
        "extension": [
          {
            "url": "http://hl7.org/fhir/us/core/StructureDefinition/us-core-race",
            "extension": [
              {
                "url": "ombCategory",
                "valueCoding": {
                  "system": "urn:oid:2.16.840.1.113883.6.238",
                  "code": "2106-3",
                  "display": "White"
                }
              },
              {
                "url": "text",
                "valueString": "White"
              }
            ]
          },
          {
            "url": "http://hl7.org/fhir/us/core/StructureDefinition/us-core-ethnicity",
            "extension": [
              {
                "url": "ombCategory",
                "valueCoding": {
                  "system": "urn:oid:2.16.840.1.113883.6.238",
                  "code": "2186-5",
                  "display": "Not Hispanic or Latino"
                }
              },
              {
                "url": "text",
                "valueString": "Not Hispanic or Latino"
              }
            ]
          },
          {
            "url": "http://hl7.org/fhir/us/core/StructureDefinition/us-core-birthsex",
            "valueCode": "F"
          }
        ],
        "identifier": [
          {
            "use": "official",
            "system": "https://parkerapex.com/gpx",
            "value": "GPX-SYN-0000000132-1",
            "assigner": {
              "display": "APEX Atlas Synthetic Population"
            }
          }
        ],
        "name": [
          {
            "use": "official",
            "family": "Jones",
            "given": [
              "Karen"
            ]
          }
        ],
        "gender": "female",
        "birthDate": "2004-11-11"
      },
      "request": {
        "method": "POST",
        "url": "Patient"
      }
    },
    {
      "fullUrl": "urn:uuid:54d8412e-f425-5f79-9fde-fee6dbf75edb",
      "resource": {
        "resourceType": "Organization",
        "id": "e0e988f1-dcf6-5e3f-bf35-f9f9f2cc0d6d",
        "meta": {
          "profile": [
            "http://hl7.org/fhir/us/core/StructureDefinition/us-core-organization|6.1.0"
          ],
          "tag": [
            {
              "system": "http://terminology.hl7.org/CodeSystem/v3-ActReason",
              "code": "HTEST",
              "display": "test health data"
            }
          ]
        },
        "identifier": [
          {
            "system": "https://parkerapex.com/atlas/payer",
            "value": "commercial-syn-aetna"
          }
        ],
        "active": true,
        "type": [
          {
            "coding": [
              {
                "system": "http://terminology.hl7.org/CodeSystem/v3-RoleCode",
                "code": "pay",
                "display": "Payer"
              }
            ]
          }
        ],
        "name": "Synthetic National Health Plan"
      },
      "request": {
        "method": "POST",
        "url": "Organization"
      }
    },
    {
      "fullUrl": "urn:uuid:971bf0bb-f483-5884-9b75-a2541025ae5f",
      "resource": {
        "resourceType": "InsurancePlan",
        "id": "60f74a9a-ab72-5f9a-83fc-ec3aa984461b",
        "meta": {
          "tag": [
            {
              "system": "http://terminology.hl7.org/CodeSystem/v3-ActReason",
              "code": "HTEST",
              "display": "test health data"
            }
          ]
        },
        "identifier": [
          {
            "system": "https://parkerapex.com/atlas/insurance-plan",
            "value": "commercial-syn-aetna"
          }
        ],
        "status": "active",
        "type": [
          {
            "coding": [
              {
                "system": "http://terminology.hl7.org/CodeSystem/insurance-plan-type",
                "code": "medical",
                "display": "Medical"
              }
            ]
          }
        ],
        "name": "Synthetic National Health Plan",
        "ownedBy": {
          "reference": "urn:uuid:54d8412e-f425-5f79-9fde-fee6dbf75edb"
        }
      },
      "request": {
        "method": "POST",
        "url": "InsurancePlan"
      }
    },
    {
      "fullUrl": "urn:uuid:6d2604b0-8843-5267-929c-a7862e614169",
      "resource": {
        "resourceType": "Coverage",
        "id": "45028cf6-a12c-5f06-880e-36aa697d6254",
        "meta": {
          "profile": [
            "http://hl7.org/fhir/us/core/StructureDefinition/us-core-coverage|6.1.0"
          ],
          "tag": [
            {
              "system": "http://terminology.hl7.org/CodeSystem/v3-ActReason",
              "code": "HTEST",
              "display": "test health data"
            }
          ]
        },
        "identifier": [
          {
            "system": "https://parkerapex.com/atlas/coverage",
            "value": "45028cf6-a12c-5f06-880e-36aa697d6254"
          }
        ],
        "status": "active",
        "type": {
          "coding": [
            {
              "system": "https://nahdo.org/sopt",
              "code": "5",
              "display": "Private Health Insurance"
            }
          ],
          "text": "Private Health Insurance"
        },
        "subscriber": {
          "reference": "urn:uuid:57e6cb1e-9930-5520-8c92-845afe5b38e3"
        },
        "subscriberId": "SYN-4610B679FE",
        "beneficiary": {
          "reference": "urn:uuid:57e6cb1e-9930-5520-8c92-845afe5b38e3"
        },
        "relationship": {
          "coding": [
            {
              "system": "http://terminology.hl7.org/CodeSystem/subscriber-relationship",
              "code": "self",
              "display": "Self"
            }
          ]
        },
        "payor": [
          {
            "reference": "urn:uuid:54d8412e-f425-5f79-9fde-fee6dbf75edb"
          }
        ],
        "order": 1,
        "class": [
          {
            "type": {
              "coding": [
                {
                  "system": "http://terminology.hl7.org/CodeSystem/coverage-class",
                  "code": "plan",
                  "display": "Plan"
                }
              ]
            },
            "value": "commercial-syn-aetna",
            "name": "commercial-syn-aetna"
          }
        ]
      },
      "request": {
        "method": "POST",
        "url": "Coverage"
      }
    },
    {
      "fullUrl": "urn:uuid:c609aee7-2dc6-53c9-be86-a71a3d487e32",
      "resource": {
        "resourceType": "Condition",
        "id": "e28de3c9-e589-5b1c-b3ee-21a03807358b",
        "meta": {
          "profile": [
            "http://hl7.org/fhir/us/core/StructureDefinition/us-core-condition-problems-health-concerns|6.1.0"
          ],
          "tag": [
            {
              "system": "http://terminology.hl7.org/CodeSystem/v3-ActReason",
              "code": "HTEST",
              "display": "test health data"
            }
          ]
        },
        "clinicalStatus": {
          "coding": [
            {
              "system": "http://terminology.hl7.org/CodeSystem/condition-clinical",
              "code": "active",
              "display": "Active"
            }
          ]
        },
        "verificationStatus": {
          "coding": [
            {
              "system": "http://terminology.hl7.org/CodeSystem/condition-ver-status",
              "code": "confirmed",
              "display": "Confirmed"
            }
          ]
        },
        "category": [
          {
            "coding": [
              {
                "system": "http://terminology.hl7.org/CodeSystem/condition-category",
                "code": "problem-list-item",
                "display": "Problem List Item"
              }
            ]
          }
        ],
        "code": {
          "coding": [
            {
              "system": "http://snomed.info/sct",
              "code": "59621000",
              "display": "Essential hypertension (disorder)"
            }
          ],
          "text": "Essential hypertension (disorder)"
        },
        "subject": {
          "reference": "urn:uuid:57e6cb1e-9930-5520-8c92-845afe5b38e3"
        },
        "onsetDateTime": "2026-06-21"
      },
      "request": {
        "method": "POST",
        "url": "Condition"
      }
    },
    {
      "fullUrl": "urn:uuid:b3d30863-7430-5e9e-93e8-08dff8a57e49",
      "resource": {
        "resourceType": "Organization",
        "id": "958813c1-7c25-555c-82e0-78b9fcabc4db",
        "meta": {
          "profile": [
            "http://hl7.org/fhir/us/core/StructureDefinition/us-core-organization|6.1.0"
          ],
          "tag": [
            {
              "system": "http://terminology.hl7.org/CodeSystem/v3-ActReason",
              "code": "HTEST",
              "display": "test health data"
            }
          ]
        },
        "identifier": [
          {
            "system": "http://hl7.org/fhir/sid/us-npi",
            "value": "2000000028"
          }
        ],
        "active": true,
        "type": [
          {
            "coding": [
              {
                "system": "http://terminology.hl7.org/CodeSystem/v3-RoleCode",
                "code": "prov",
                "display": "Healthcare Provider"
              }
            ]
          }
        ],
        "name": "APEX Atlas Cardiology Clinic"
      },
      "request": {
        "method": "POST",
        "url": "Organization"
      }
    },
    {
      "fullUrl": "urn:uuid:c5094722-38fe-5900-8d4d-8c8a4d328ec6",
      "resource": {
        "resourceType": "Practitioner",
        "id": "e29bc37d-dc84-5717-82db-454f89fea2a2",
        "meta": {
          "profile": [
            "http://hl7.org/fhir/us/core/StructureDefinition/us-core-practitioner|6.1.0"
          ],
          "tag": [
            {
              "system": "http://terminology.hl7.org/CodeSystem/v3-ActReason",
              "code": "HTEST",
              "display": "test health data"
            }
          ]
        },
        "identifier": [
          {
            "system": "http://hl7.org/fhir/sid/us-npi",
            "value": "1000000020"
          }
        ],
        "active": true,
        "name": [
          {
            "family": "Nguyen",
            "given": [
              "Linh"
            ],
            "prefix": [
              "Dr."
            ]
          }
        ]
      },
      "request": {
        "method": "POST",
        "url": "Practitioner"
      }
    },
    {
      "fullUrl": "urn:uuid:f0a0f430-f88e-5f92-9203-99623e54b979",
      "resource": {
        "resourceType": "Location",
        "id": "dfcd7fce-e993-551a-84bc-1a335208e4f9",
        "meta": {
          "profile": [
            "http://hl7.org/fhir/us/core/StructureDefinition/us-core-location|6.1.0"
          ],
          "tag": [
            {
              "system": "http://terminology.hl7.org/CodeSystem/v3-ActReason",
              "code": "HTEST",
              "display": "test health data"
            }
          ]
        },
        "status": "active",
        "name": "Outpatient Cardiology",
        "type": [
          {
            "coding": [
              {
                "system": "http://terminology.hl7.org/CodeSystem/v3-RoleCode",
                "code": "OF",
                "display": "Outpatient Facility"
              }
            ],
            "text": "Outpatient Facility"
          }
        ],
        "address": {
          "use": "work",
          "line": [
            "250 Beacon St"
          ],
          "city": "Boston",
          "state": "MA",
          "postalCode": "02116",
          "country": "US"
        },
        "managingOrganization": {
          "reference": "urn:uuid:b3d30863-7430-5e9e-93e8-08dff8a57e49"
        }
      },
      "request": {
        "method": "POST",
        "url": "Location"
      }
    },
    {
      "fullUrl": "urn:uuid:e01c3123-3c08-52be-a282-1b33ff5b3b73",
      "resource": {
        "resourceType": "PractitionerRole",
        "id": "ab5832c7-e9f8-517a-9fd9-f8af3e677791",
        "meta": {
          "profile": [
            "http://hl7.org/fhir/us/core/StructureDefinition/us-core-practitionerrole|6.1.0"
          ],
          "tag": [
            {
              "system": "http://terminology.hl7.org/CodeSystem/v3-ActReason",
              "code": "HTEST",
              "display": "test health data"
            }
          ]
        },
        "active": true,
        "practitioner": {
          "reference": "urn:uuid:c5094722-38fe-5900-8d4d-8c8a4d328ec6"
        },
        "organization": {
          "reference": "urn:uuid:b3d30863-7430-5e9e-93e8-08dff8a57e49"
        },
        "specialty": [
          {
            "coding": [
              {
                "system": "http://nucc.org/provider-taxonomy",
                "code": "207Q00000X",
                "display": "Family Medicine"
              }
            ],
            "text": "Family Medicine"
          }
        ]
      },
      "request": {
        "method": "POST",
        "url": "PractitionerRole"
      }
    },
    {
      "fullUrl": "urn:uuid:42522e0c-5269-53d0-b65e-46807172cfb8",
      "resource": {
        "resourceType": "Encounter",
        "id": "fe2d65ed-d475-5025-a8bc-664e52ed6864",
        "meta": {
          "profile": [
            "http://hl7.org/fhir/us/core/StructureDefinition/us-core-encounter|6.1.0"
          ],
          "tag": [
            {
              "system": "http://terminology.hl7.org/CodeSystem/v3-ActReason",
              "code": "HTEST",
              "display": "test health data"
            }
          ]
        },
        "identifier": [
          {
            "system": "https://parkerapex.com/atlas/encounter",
            "value": "fe2d65ed-d475-5025-a8bc-664e52ed6864"
          }
        ],
        "status": "finished",
        "class": {
          "system": "http://terminology.hl7.org/CodeSystem/v3-ActCode",
          "code": "AMB",
          "display": "ambulatory"
        },
        "type": [
          {
            "coding": [
              {
                "system": "http://snomed.info/sct",
                "code": "185349003",
                "display": "Encounter for check up"
              }
            ],
            "text": "Encounter for check up"
          }
        ],
        "subject": {
          "reference": "urn:uuid:57e6cb1e-9930-5520-8c92-845afe5b38e3"
        },
        "period": {
          "start": "2026-06-21",
          "end": "2026-06-21"
        },
        "participant": [
          {
            "type": [
              {
                "coding": [
                  {
                    "system": "http://terminology.hl7.org/CodeSystem/v3-ParticipationType",
                    "code": "ATND",
                    "display": "attender"
                  }
                ]
              }
            ],
            "individual": {
              "reference": "urn:uuid:c5094722-38fe-5900-8d4d-8c8a4d328ec6"
            }
          }
        ],
        "location": [
          {
            "location": {
              "reference": "urn:uuid:f0a0f430-f88e-5f92-9203-99623e54b979"
            },
            "status": "completed"
          }
        ],
        "serviceProvider": {
          "reference": "urn:uuid:b3d30863-7430-5e9e-93e8-08dff8a57e49"
        },
        "reasonCode": [
          {
            "coding": [
              {
                "system": "http://snomed.info/sct",
                "code": "59621000",
                "display": "Essential hypertension"
              }
            ],
            "text": "Essential hypertension"
          }
        ]
      },
      "request": {
        "method": "POST",
        "url": "Encounter"
      }
    },
    {
      "fullUrl": "urn:uuid:22edec61-448d-5da6-bc14-2da33c158817",
      "resource": {
        "resourceType": "Organization",
        "id": "b3a1bbac-67d3-5925-afe7-a4be8793998f",
        "meta": {
          "profile": [
            "http://hl7.org/fhir/us/core/StructureDefinition/us-core-organization|6.1.0"
          ],
          "tag": [
            {
              "system": "http://terminology.hl7.org/CodeSystem/v3-ActReason",
              "code": "HTEST",
              "display": "test health data"
            }
          ]
        },
        "identifier": [
          {
            "system": "http://hl7.org/fhir/sid/us-npi",
            "value": "2000000044"
          }
        ],
        "active": true,
        "type": [
          {
            "coding": [
              {
                "system": "http://terminology.hl7.org/CodeSystem/v3-RoleCode",
                "code": "prov",
                "display": "Healthcare Provider"
              }
            ]
          }
        ],
        "name": "APEX Atlas Primary Care - Somerville"
      },
      "request": {
        "method": "POST",
        "url": "Organization"
      }
    },
    {
      "fullUrl": "urn:uuid:a93dcd0b-6a8f-5dc6-80a8-65d896d255fe",
      "resource": {
        "resourceType": "Practitioner",
        "id": "13a622f4-c249-52e9-ba67-805c3615063b",
        "meta": {
          "profile": [
            "http://hl7.org/fhir/us/core/StructureDefinition/us-core-practitioner|6.1.0"
          ],
          "tag": [
            {
              "system": "http://terminology.hl7.org/CodeSystem/v3-ActReason",
              "code": "HTEST",
              "display": "test health data"
            }
          ]
        },
        "identifier": [
          {
            "system": "http://hl7.org/fhir/sid/us-npi",
            "value": "1000000046"
          }
        ],
        "active": true,
        "name": [
          {
            "family": "Okafor",
            "given": [
              "Chinwe"
            ],
            "prefix": [
              "Dr."
            ]
          }
        ]
      },
      "request": {
        "method": "POST",
        "url": "Practitioner"
      }
    },
    {
      "fullUrl": "urn:uuid:067768ea-1235-51f6-be2a-cb25e2c9eae2",
      "resource": {
        "resourceType": "Location",
        "id": "b1d3099a-b78d-5033-98c5-8cda15a47bff",
        "meta": {
          "profile": [
            "http://hl7.org/fhir/us/core/StructureDefinition/us-core-location|6.1.0"
          ],
          "tag": [
            {
              "system": "http://terminology.hl7.org/CodeSystem/v3-ActReason",
              "code": "HTEST",
              "display": "test health data"
            }
          ]
        },
        "status": "active",
        "name": "Primary Care Suite",
        "type": [
          {
            "coding": [
              {
                "system": "http://terminology.hl7.org/CodeSystem/v3-RoleCode",
                "code": "OF",
                "display": "Outpatient Facility"
              }
            ],
            "text": "Outpatient Facility"
          }
        ],
        "address": {
          "use": "work",
          "line": [
            "300 Highland Ave"
          ],
          "city": "Somerville",
          "state": "MA",
          "postalCode": "02143",
          "country": "US"
        },
        "managingOrganization": {
          "reference": "urn:uuid:22edec61-448d-5da6-bc14-2da33c158817"
        }
      },
      "request": {
        "method": "POST",
        "url": "Location"
      }
    },
    {
      "fullUrl": "urn:uuid:1dd29ba1-c8b4-5f49-bfe4-edb468a4036c",
      "resource": {
        "resourceType": "PractitionerRole",
        "id": "af8dcb45-9dfb-58ef-b076-bbd070be1683",
        "meta": {
          "profile": [
            "http://hl7.org/fhir/us/core/StructureDefinition/us-core-practitionerrole|6.1.0"
          ],
          "tag": [
            {
              "system": "http://terminology.hl7.org/CodeSystem/v3-ActReason",
              "code": "HTEST",
              "display": "test health data"
            }
          ]
        },
        "active": true,
        "practitioner": {
          "reference": "urn:uuid:a93dcd0b-6a8f-5dc6-80a8-65d896d255fe"
        },
        "organization": {
          "reference": "urn:uuid:22edec61-448d-5da6-bc14-2da33c158817"
        },
        "specialty": [
          {
            "coding": [
              {
                "system": "http://nucc.org/provider-taxonomy",
                "code": "207RC0000X",
                "display": "Cardiovascular Disease"
              }
            ],
            "text": "Cardiovascular Disease"
          }
        ]
      },
      "request": {
        "method": "POST",
        "url": "PractitionerRole"
      }
    },
    {
      "fullUrl": "urn:uuid:f250b1ef-cb67-5d8b-b2db-e7fa797a2978",
      "resource": {
        "resourceType": "Encounter",
        "id": "f08da885-6994-53ec-900f-3409cdd6691d",
        "meta": {
          "profile": [
            "http://hl7.org/fhir/us/core/StructureDefinition/us-core-encounter|6.1.0"
          ],
          "tag": [
            {
              "system": "http://terminology.hl7.org/CodeSystem/v3-ActReason",
              "code": "HTEST",
              "display": "test health data"
            }
          ]
        },
        "identifier": [
          {
            "system": "https://parkerapex.com/atlas/encounter",
            "value": "f08da885-6994-53ec-900f-3409cdd6691d"
          }
        ],
        "status": "finished",
        "class": {
          "system": "http://terminology.hl7.org/CodeSystem/v3-ActCode",
          "code": "AMB",
          "display": "ambulatory"
        },
        "type": [
          {
            "coding": [
              {
                "system": "http://snomed.info/sct",
                "code": "390906007",
                "display": "Follow-up encounter"
              }
            ],
            "text": "Follow-up encounter"
          }
        ],
        "subject": {
          "reference": "urn:uuid:57e6cb1e-9930-5520-8c92-845afe5b38e3"
        },
        "period": {
          "start": "2026-06-21",
          "end": "2026-06-21"
        },
        "participant": [
          {
            "type": [
              {
                "coding": [
                  {
                    "system": "http://terminology.hl7.org/CodeSystem/v3-ParticipationType",
                    "code": "ATND",
                    "display": "attender"
                  }
                ]
              }
            ],
            "individual": {
              "reference": "urn:uuid:a93dcd0b-6a8f-5dc6-80a8-65d896d255fe"
            }
          }
        ],
        "location": [
          {
            "location": {
              "reference": "urn:uuid:067768ea-1235-51f6-be2a-cb25e2c9eae2"
            },
            "status": "completed"
          }
        ],
        "serviceProvider": {
          "reference": "urn:uuid:22edec61-448d-5da6-bc14-2da33c158817"
        },
        "reasonCode": [
          {
            "coding": [
              {
                "system": "http://snomed.info/sct",
                "code": "59621000",
                "display": "Essential hypertension"
              }
            ],
            "text": "Essential hypertension"
          }
        ]
      },
      "request": {
        "method": "POST",
        "url": "Encounter"
      }
    },
    {
      "fullUrl": "urn:uuid:ec6d0fcc-6f24-5bb1-8414-cfb224145f5b",
      "resource": {
        "resourceType": "Observation",
        "id": "e155e276-515c-5de8-bff2-038de9d88b20",
        "meta": {
          "tag": [
            {
              "system": "http://terminology.hl7.org/CodeSystem/v3-ActReason",
              "code": "HTEST",
              "display": "test health data"
            }
          ],
          "profile": [
            "http://hl7.org/fhir/us/core/StructureDefinition/us-core-blood-pressure|6.1.0"
          ]
        },
        "status": "final",
        "category": [
          {
            "coding": [
              {
                "system": "http://terminology.hl7.org/CodeSystem/observation-category",
                "code": "vital-signs",
                "display": "Vital Signs"
              }
            ]
          }
        ],
        "code": {
          "coding": [
            {
              "system": "http://loinc.org",
              "code": "85354-9",
              "display": "Blood pressure panel with all children optional"
            }
          ],
          "text": "Blood pressure panel with all children optional"
        },
        "subject": {
          "reference": "urn:uuid:57e6cb1e-9930-5520-8c92-845afe5b38e3"
        },
        "effectiveDateTime": "2026-06-21",
        "component": [
          {
            "code": {
              "coding": [
                {
                  "system": "http://loinc.org",
                  "code": "8480-6",
                  "display": "Systolic blood pressure"
                }
              ],
              "text": "Systolic blood pressure"
            },
            "valueQuantity": {
              "value": 142.0,
              "unit": "mm[Hg]",
              "system": "http://unitsofmeasure.org",
              "code": "mm[Hg]"
            }
          },
          {
            "code": {
              "coding": [
                {
                  "system": "http://loinc.org",
                  "code": "8462-4",
                  "display": "Diastolic blood pressure"
                }
              ],
              "text": "Diastolic blood pressure"
            },
            "valueQuantity": {
              "value": 96.0,
              "unit": "mm[Hg]",
              "system": "http://unitsofmeasure.org",
              "code": "mm[Hg]"
            }
          }
        ],
        "encounter": {
          "reference": "urn:uuid:42522e0c-5269-53d0-b65e-46807172cfb8"
        }
      },
      "request": {
        "method": "POST",
        "url": "Observation"
      }
    },
    {
      "fullUrl": "urn:uuid:81a42e6f-dc56-5e50-9786-99cd836e3bf6",
      "resource": {
        "resourceType": "MedicationRequest",
        "id": "edb0f6ae-81a1-5f45-8705-2e107ac5ff50",
        "meta": {
          "profile": [
            "http://hl7.org/fhir/us/core/StructureDefinition/us-core-medicationrequest|6.1.0"
          ],
          "tag": [
            {
              "system": "http://terminology.hl7.org/CodeSystem/v3-ActReason",
              "code": "HTEST",
              "display": "test health data"
            }
          ]
        },
        "status": "active",
        "intent": "order",
        "medicationCodeableConcept": {
          "coding": [
            {
              "system": "http://www.nlm.nih.gov/research/umls/rxnorm",
              "code": "197361",
              "display": "Lisinopril 10 MG Oral Tablet"
            }
          ],
          "text": "Lisinopril 10 MG Oral Tablet"
        },
        "subject": {
          "reference": "urn:uuid:57e6cb1e-9930-5520-8c92-845afe5b38e3"
        },
        "authoredOn": "2026-06-21",
        "reasonCode": [
          {
            "coding": [
              {
                "system": "http://snomed.info/sct",
                "code": "59621000",
                "display": "Essential hypertension"
              }
            ],
            "text": "Essential hypertension"
          }
        ],
        "encounter": {
          "reference": "urn:uuid:42522e0c-5269-53d0-b65e-46807172cfb8"
        }
      },
      "request": {
        "method": "POST",
        "url": "MedicationRequest"
      }
    },
    {
      "fullUrl": "urn:uuid:cc9ae275-ae85-511e-8f56-cb5e8be07db1",
      "resource": {
        "resourceType": "Observation",
        "id": "55a97118-adcd-5891-88eb-504ccc8020b9",
        "meta": {
          "tag": [
            {
              "system": "http://terminology.hl7.org/CodeSystem/v3-ActReason",
              "code": "HTEST",
              "display": "test health data"
            }
          ],
          "profile": [
            "http://hl7.org/fhir/us/core/StructureDefinition/us-core-blood-pressure|6.1.0"
          ]
        },
        "status": "final",
        "category": [
          {
            "coding": [
              {
                "system": "http://terminology.hl7.org/CodeSystem/observation-category",
                "code": "vital-signs",
                "display": "Vital Signs"
              }
            ]
          }
        ],
        "code": {
          "coding": [
            {
              "system": "http://loinc.org",
              "code": "85354-9",
              "display": "Blood pressure panel with all children optional"
            }
          ],
          "text": "Blood pressure panel with all children optional"
        },
        "subject": {
          "reference": "urn:uuid:57e6cb1e-9930-5520-8c92-845afe5b38e3"
        },
        "effectiveDateTime": "2026-06-21",
        "component": [
          {
            "code": {
              "coding": [
                {
                  "system": "http://loinc.org",
                  "code": "8480-6",
                  "display": "Systolic blood pressure"
                }
              ],
              "text": "Systolic blood pressure"
            },
            "valueQuantity": {
              "value": 121.0,
              "unit": "mm[Hg]",
              "system": "http://unitsofmeasure.org",
              "code": "mm[Hg]"
            }
          },
          {
            "code": {
              "coding": [
                {
                  "system": "http://loinc.org",
                  "code": "8462-4",
                  "display": "Diastolic blood pressure"
                }
              ],
              "text": "Diastolic blood pressure"
            },
            "valueQuantity": {
              "value": 90.0,
              "unit": "mm[Hg]",
              "system": "http://unitsofmeasure.org",
              "code": "mm[Hg]"
            }
          }
        ],
        "encounter": {
          "reference": "urn:uuid:f250b1ef-cb67-5d8b-b2db-e7fa797a2978"
        }
      },
      "request": {
        "method": "POST",
        "url": "Observation"
      }
    },
    {
      "fullUrl": "urn:uuid:127469be-b476-599d-9e88-6476b5646847",
      "resource": {
        "resourceType": "DocumentReference",
        "id": "8b70f711-9c28-52ca-8cd1-8a3682a53de7",
        "meta": {
          "tag": [
            {
              "system": "http://terminology.hl7.org/CodeSystem/v3-ActReason",
              "code": "HTEST",
              "display": "test health data"
            }
          ]
        },
        "status": "current",
        "type": {
          "coding": [
            {
              "system": "http://loinc.org",
              "code": "11506-3",
              "display": "Progress note"
            }
          ],
          "text": "Progress note"
        },
        "category": [
          {
            "coding": [
              {
                "system": "http://loinc.org",
                "code": "47039-3",
                "display": "Hospital Admission history and physical note"
              }
            ]
          }
        ],
        "subject": {
          "reference": "urn:uuid:57e6cb1e-9930-5520-8c92-845afe5b38e3"
        },
        "date": "2026-06-21T12:00:00+00:00",
        "content": [
          {
            "attachment": {
              "contentType": "text/markdown",
              "data": "IyBQcm9ncmVzcyBOb3RlCgoqKlBhdGllbnQ6KiogSm9uZXMsIEthcmVuCioqQWdlIC8gU2V4OioqIDIxIC8gZmVtYWxlCioqRGF0ZToqKiAyMDI2LTA2LTIxCgojIyBBY3RpdmUgUHJvYmxlbXMKLSBFc3NlbnRpYWwgaHlwZXJ0ZW5zaW9uIChkaXNvcmRlcikgKGh0dHA6Ly9zbm9tZWQuaW5mby9zY3QgNTk2MjEwMDApIChvbnNldCAyMDI2LTA2LTIxKQoKIyMgU3ViamVjdGl2ZQpQYXRpZW50IHNlZW4gdG9kYXkgZm9yIGZvbGxvdy11cCBvZiBFc3NlbnRpYWwgaHlwZXJ0ZW5zaW9uIChkaXNvcmRlcikuCk5vIG5ldyBhY3V0ZSBjb21wbGFpbnRzIGRvY3VtZW50ZWQgaW4gdGhpcyBzeW50aGV0aWMgcmVjb3JkLgoKIyMgT2JqZWN0aXZlCgojIyMgVml0YWxzICYgbGFicyAobW9zdCByZWNlbnQpCi0gQmxvb2QgcHJlc3N1cmU6IDE0Mi85NiBtbUhnICgyMDI2LTA2LTIxKQoKIyMjIEFjdGl2ZSBtZWRpY2F0aW9ucwotIExpc2lub3ByaWwgMTAgTUcgT3JhbCBUYWJsZXQKCiMjIEFzc2Vzc21lbnQgJiBQbGFuCkNvbnRpbnVlIGN1cnJlbnQgbWFuYWdlbWVudCBvZiBFc3NlbnRpYWwgaHlwZXJ0ZW5zaW9uIChkaXNvcmRlcikuIFJlYXNzZXNzIGF0IG5leHQgcm91dGluZSBmb2xsb3ctdXAuCgotLS0KX0dlbmVyYXRlZCBieSBBUEVYIEF0bGFzICh0ZW1wbGF0ZSBtb2RlKS4gVGhpcyBpcyBzeW50aGV0aWMgZGF0YTsgbm8gcmVhbCBwYXRpZW50IGlzIGRlcGljdGVkLl8="
            }
          }
        ],
        "context": {
          "encounter": [
            {
              "reference": "urn:uuid:42522e0c-5269-53d0-b65e-46807172cfb8"
            }
          ]
        }
      },
      "request": {
        "method": "POST",
        "url": "DocumentReference"
      }
    },
    {
      "fullUrl": "urn:uuid:a1117fc0-dbd7-5a8e-a85f-5bb0d868796e",
      "resource": {
        "resourceType": "Observation",
        "id": "09dff61d-5ac2-527f-86ee-ca116cc4bb5b",
        "meta": {
          "profile": [
            "http://hl7.org/fhir/us/sdoh-clinicalcare/StructureDefinition/SDOHCC-ObservationScreeningResponse"
          ],
          "tag": [
            {
              "system": "http://terminology.hl7.org/CodeSystem/v3-ActReason",
              "code": "HTEST",
              "display": "test health data"
            }
          ]
        },
        "status": "final",
        "category": [
          {
            "coding": [
              {
                "system": "http://terminology.hl7.org/CodeSystem/observation-category",
                "code": "social-history",
                "display": "Social History"
              }
            ]
          },
          {
            "coding": [
              {
                "system": "http://hl7.org/fhir/us/sdoh-clinicalcare/CodeSystem/SDOHCC-CodeSystemTemporaryCodes",
                "code": "food-insecurity",
                "display": "Food Insecurity"
              }
            ]
          }
        ],
        "code": {
          "coding": [
            {
              "system": "http://loinc.org",
              "code": "88122-0",
              "display": "Within the past 12 months, we worried whether our food would run out"
            }
          ],
          "text": "Within the past 12 months, we worried whether our food would run out"
        },
        "subject": {
          "reference": "urn:uuid:57e6cb1e-9930-5520-8c92-845afe5b38e3"
        },
        "effectiveDateTime": "2026-06-21",
        "valueCodeableConcept": {
          "coding": [
            {
              "system": "http://loinc.org",
              "code": "LA32-8",
              "display": "No"
            }
          ],
          "text": "No"
        }
      },
      "request": {
        "method": "POST",
        "url": "Observation"
      }
    },
    {
      "fullUrl": "urn:uuid:633e9ffc-a522-5b62-b9fe-d48d8a684801",
      "resource": {
        "resourceType": "Observation",
        "id": "0af60e5c-1128-57e3-957c-7f631c8c2dfa",
        "meta": {
          "profile": [
            "http://hl7.org/fhir/us/sdoh-clinicalcare/StructureDefinition/SDOHCC-ObservationScreeningResponse"
          ],
          "tag": [
            {
              "system": "http://terminology.hl7.org/CodeSystem/v3-ActReason",
              "code": "HTEST",
              "display": "test health data"
            }
          ]
        },
        "status": "final",
        "category": [
          {
            "coding": [
              {
                "system": "http://terminology.hl7.org/CodeSystem/observation-category",
                "code": "social-history",
                "display": "Social History"
              }
            ]
          },
          {
            "coding": [
              {
                "system": "http://hl7.org/fhir/us/sdoh-clinicalcare/CodeSystem/SDOHCC-CodeSystemTemporaryCodes",
                "code": "housing-instability",
                "display": "Housing Instability"
              }
            ]
          }
        ],
        "code": {
          "coding": [
            {
              "system": "http://loinc.org",
              "code": "71802-3",
              "display": "What is your living situation today?"
            }
          ],
          "text": "What is your living situation today?"
        },
        "subject": {
          "reference": "urn:uuid:57e6cb1e-9930-5520-8c92-845afe5b38e3"
        },
        "effectiveDateTime": "2026-06-21",
        "valueCodeableConcept": {
          "coding": [
            {
              "system": "http://loinc.org",
              "code": "LA31994-9",
              "display": "I have housing"
            }
          ],
          "text": "I have housing"
        }
      },
      "request": {
        "method": "POST",
        "url": "Observation"
      }
    },
    {
      "fullUrl": "urn:uuid:6b4ded03-8707-50f9-a225-0d8a69904f1c",
      "resource": {
        "resourceType": "Observation",
        "id": "79e634f3-8aa3-5c27-ae5e-fffea6e633e9",
        "meta": {
          "profile": [
            "http://hl7.org/fhir/us/sdoh-clinicalcare/StructureDefinition/SDOHCC-ObservationScreeningResponse"
          ],
          "tag": [
            {
              "system": "http://terminology.hl7.org/CodeSystem/v3-ActReason",
              "code": "HTEST",
              "display": "test health data"
            }
          ]
        },
        "status": "final",
        "category": [
          {
            "coding": [
              {
                "system": "http://terminology.hl7.org/CodeSystem/observation-category",
                "code": "social-history",
                "display": "Social History"
              }
            ]
          },
          {
            "coding": [
              {
                "system": "http://hl7.org/fhir/us/sdoh-clinicalcare/CodeSystem/SDOHCC-CodeSystemTemporaryCodes",
                "code": "transportation-insecurity",
                "display": "Transportation Insecurity"
              }
            ]
          }
        ],
        "code": {
          "coding": [
            {
              "system": "http://loinc.org",
              "code": "93030-5",
              "display": "Has lack of transportation kept you from medical appointments, meetings, work, or from getting things needed for daily living?"
            }
          ],
          "text": "Has lack of transportation kept you from medical appointments, meetings, work, or from getting things needed for daily living?"
        },
        "subject": {
          "reference": "urn:uuid:57e6cb1e-9930-5520-8c92-845afe5b38e3"
        },
        "effectiveDateTime": "2026-06-21",
        "valueCodeableConcept": {
          "coding": [
            {
              "system": "http://loinc.org",
              "code": "LA33-6",
              "display": "Yes"
            }
          ],
          "text": "Yes"
        }
      },
      "request": {
        "method": "POST",
        "url": "Observation"
      }
    },
    {
      "fullUrl": "urn:uuid:29691c2e-e4cf-594c-aba0-bd7a0d4a416b",
      "resource": {
        "resourceType": "Observation",
        "id": "26e0ab9f-cac6-524d-8d6c-0a736b0c47b7",
        "meta": {
          "profile": [
            "http://hl7.org/fhir/us/sdoh-clinicalcare/StructureDefinition/SDOHCC-ObservationScreeningResponse"
          ],
          "tag": [
            {
              "system": "http://terminology.hl7.org/CodeSystem/v3-ActReason",
              "code": "HTEST",
              "display": "test health data"
            }
          ]
        },
        "status": "final",
        "category": [
          {
            "coding": [
              {
                "system": "http://terminology.hl7.org/CodeSystem/observation-category",
                "code": "social-history",
                "display": "Social History"
              }
            ]
          },
          {
            "coding": [
              {
                "system": "http://hl7.org/fhir/us/sdoh-clinicalcare/CodeSystem/SDOHCC-CodeSystemTemporaryCodes",
                "code": "financial-insecurity",
                "display": "Financial Insecurity"
              }
            ]
          }
        ],
        "code": {
          "coding": [
            {
              "system": "http://loinc.org",
              "code": "96780-2",
              "display": "Do you want help finding or keeping work or a job?"
            }
          ],
          "text": "Do you want help finding or keeping work or a job?"
        },
        "subject": {
          "reference": "urn:uuid:57e6cb1e-9930-5520-8c92-845afe5b38e3"
        },
        "effectiveDateTime": "2026-06-21",
        "valueCodeableConcept": {
          "coding": [
            {
              "system": "http://loinc.org",
              "code": "LA33-6",
              "display": "Yes, help finding work"
            }
          ],
          "text": "Yes, help finding work"
        }
      },
      "request": {
        "method": "POST",
        "url": "Observation"
      }
    },
    {
      "fullUrl": "urn:uuid:e9c521e6-a3ee-5454-9032-2927058ddaa5",
      "resource": {
        "resourceType": "Observation",
        "id": "8be26307-b2ee-5ec4-8586-29cfed0c80c2",
        "meta": {
          "profile": [
            "http://hl7.org/fhir/us/sdoh-clinicalcare/StructureDefinition/SDOHCC-ObservationScreeningResponse"
          ],
          "tag": [
            {
              "system": "http://terminology.hl7.org/CodeSystem/v3-ActReason",
              "code": "HTEST",
              "display": "test health data"
            }
          ]
        },
        "status": "final",
        "category": [
          {
            "coding": [
              {
                "system": "http://terminology.hl7.org/CodeSystem/observation-category",
                "code": "social-history",
                "display": "Social History"
              }
            ]
          },
          {
            "coding": [
              {
                "system": "http://hl7.org/fhir/us/sdoh-clinicalcare/CodeSystem/SDOHCC-CodeSystemTemporaryCodes",
                "code": "social-connection",
                "display": "Social Connection"
              }
            ]
          }
        ],
        "code": {
          "coding": [
            {
              "system": "http://loinc.org",
              "code": "54899-0",
              "display": "How often do you feel lonely or isolated from those around you?"
            }
          ],
          "text": "How often do you feel lonely or isolated from those around you?"
        },
        "subject": {
          "reference": "urn:uuid:57e6cb1e-9930-5520-8c92-845afe5b38e3"
        },
        "effectiveDateTime": "2026-06-21",
        "valueCodeableConcept": {
          "coding": [
            {
              "system": "http://loinc.org",
              "code": "LA10066-1",
              "display": "Rarely"
            }
          ],
          "text": "Rarely"
        }
      },
      "request": {
        "method": "POST",
        "url": "Observation"
      }
    },
    {
      "fullUrl": "urn:uuid:acc188ff-e716-5494-9c52-f159542a20ee",
      "resource": {
        "resourceType": "Claim",
        "id": "57468d83-ab4a-53fe-ac91-deba981e23ea",
        "meta": {
          "tag": [
            {
              "system": "http://terminology.hl7.org/CodeSystem/v3-ActReason",
              "code": "HTEST",
              "display": "test health data"
            }
          ]
        },
        "identifier": [
          {
            "system": "https://parkerapex.com/atlas/claim",
            "value": "57468d83-ab4a-53fe-ac91-deba981e23ea"
          }
        ],
        "status": "active",
        "type": {
          "coding": [
            {
              "system": "http://terminology.hl7.org/CodeSystem/claim-type",
              "code": "professional",
              "display": "Professional"
            }
          ]
        },
        "use": "claim",
        "patient": {
          "reference": "urn:uuid:57e6cb1e-9930-5520-8c92-845afe5b38e3"
        },
        "created": "2026-06-21",
        "provider": {
          "reference": "urn:uuid:b3d30863-7430-5e9e-93e8-08dff8a57e49"
        },
        "priority": {
          "coding": [
            {
              "system": "http://terminology.hl7.org/CodeSystem/processpriority",
              "code": "normal",
              "display": "Normal"
            }
          ]
        },
        "insurance": [
          {
            "sequence": 1,
            "focal": true,
            "coverage": {
              "reference": "urn:uuid:6d2604b0-8843-5267-929c-a7862e614169"
            }
          }
        ],
        "item": [
          {
            "sequence": 1,
            "productOrService": {
              "coding": [
                {
                  "system": "http://www.ama-assn.org/go/cpt",
                  "code": "99213",
                  "display": "Office outpatient visit, established patient"
                }
              ],
              "text": "Office outpatient visit, established patient"
            },
            "encounter": [
              {
                "reference": "urn:uuid:42522e0c-5269-53d0-b65e-46807172cfb8"
              }
            ],
            "unitPrice": {
              "value": 165.0,
              "currency": "USD"
            },
            "net": {
              "value": 165.0,
              "currency": "USD"
            }
          }
        ],
        "total": {
          "value": 165.0,
          "currency": "USD"
        }
      },
      "request": {
        "method": "POST",
        "url": "Claim"
      }
    },
    {
      "fullUrl": "urn:uuid:d746e842-30b5-5f31-9d8a-aa8a72a86f30",
      "resource": {
        "resourceType": "ExplanationOfBenefit",
        "id": "86e83933-9ee0-5312-b036-f9e281a3b3e3",
        "meta": {
          "tag": [
            {
              "system": "http://terminology.hl7.org/CodeSystem/v3-ActReason",
              "code": "HTEST",
              "display": "test health data"
            }
          ]
        },
        "identifier": [
          {
            "system": "https://parkerapex.com/atlas/explanation-of-benefit",
            "value": "86e83933-9ee0-5312-b036-f9e281a3b3e3"
          }
        ],
        "status": "active",
        "type": {
          "coding": [
            {
              "system": "http://terminology.hl7.org/CodeSystem/claim-type",
              "code": "professional",
              "display": "Professional"
            }
          ]
        },
        "use": "claim",
        "patient": {
          "reference": "urn:uuid:57e6cb1e-9930-5520-8c92-845afe5b38e3"
        },
        "created": "2026-06-21",
        "insurer": {
          "reference": "urn:uuid:54d8412e-f425-5f79-9fde-fee6dbf75edb"
        },
        "provider": {
          "reference": "urn:uuid:b3d30863-7430-5e9e-93e8-08dff8a57e49"
        },
        "outcome": "complete",
        "claim": {
          "reference": "urn:uuid:acc188ff-e716-5494-9c52-f159542a20ee"
        },
        "insurance": [
          {
            "focal": true,
            "coverage": {
              "reference": "urn:uuid:6d2604b0-8843-5267-929c-a7862e614169"
            }
          }
        ],
        "item": [
          {
            "sequence": 1,
            "productOrService": {
              "coding": [
                {
                  "system": "http://www.ama-assn.org/go/cpt",
                  "code": "99213",
                  "display": "Office outpatient visit, established patient"
                }
              ],
              "text": "Office outpatient visit, established patient"
            },
            "encounter": [
              {
                "reference": "urn:uuid:42522e0c-5269-53d0-b65e-46807172cfb8"
              }
            ],
            "adjudication": [
              {
                "category": {
                  "coding": [
                    {
                      "code": "submitted"
                    }
                  ]
                },
                "amount": {
                  "value": 165.0,
                  "currency": "USD"
                }
              },
              {
                "category": {
                  "coding": [
                    {
                      "code": "eligible"
                    }
                  ]
                },
                "amount": {
                  "value": 125.4,
                  "currency": "USD"
                }
              },
              {
                "category": {
                  "coding": [
                    {
                      "code": "benefit"
                    }
                  ]
                },
                "amount": {
                  "value": 100.32,
                  "currency": "USD"
                }
              },
              {
                "category": {
                  "coding": [
                    {
                      "code": "copay"
                    }
                  ]
                },
                "amount": {
                  "value": 25.08,
                  "currency": "USD"
                }
              }
            ]
          }
        ],
        "total": [
          {
            "category": {
              "coding": [
                {
                  "code": "submitted"
                }
              ]
            },
            "amount": {
              "value": 165.0,
              "currency": "USD"
            }
          },
          {
            "category": {
              "coding": [
                {
                  "code": "benefit"
                }
              ]
            },
            "amount": {
              "value": 100.32,
              "currency": "USD"
            }
          }
        ]
      },
      "request": {
        "method": "POST",
        "url": "ExplanationOfBenefit"
      }
    },
    {
      "fullUrl": "urn:uuid:9cc489c7-04b5-5522-8adb-db0b0a853152",
      "resource": {
        "resourceType": "Claim",
        "id": "bd289745-64b9-5384-971c-05791b5d671b",
        "meta": {
          "tag": [
            {
              "system": "http://terminology.hl7.org/CodeSystem/v3-ActReason",
              "code": "HTEST",
              "display": "test health data"
            }
          ]
        },
        "identifier": [
          {
            "system": "https://parkerapex.com/atlas/claim",
            "value": "bd289745-64b9-5384-971c-05791b5d671b"
          }
        ],
        "status": "active",
        "type": {
          "coding": [
            {
              "system": "http://terminology.hl7.org/CodeSystem/claim-type",
              "code": "professional",
              "display": "Professional"
            }
          ]
        },
        "use": "claim",
        "patient": {
          "reference": "urn:uuid:57e6cb1e-9930-5520-8c92-845afe5b38e3"
        },
        "created": "2026-06-21",
        "provider": {
          "reference": "urn:uuid:22edec61-448d-5da6-bc14-2da33c158817"
        },
        "priority": {
          "coding": [
            {
              "system": "http://terminology.hl7.org/CodeSystem/processpriority",
              "code": "normal",
              "display": "Normal"
            }
          ]
        },
        "insurance": [
          {
            "sequence": 1,
            "focal": true,
            "coverage": {
              "reference": "urn:uuid:6d2604b0-8843-5267-929c-a7862e614169"
            }
          }
        ],
        "item": [
          {
            "sequence": 1,
            "productOrService": {
              "coding": [
                {
                  "system": "http://www.ama-assn.org/go/cpt",
                  "code": "99213",
                  "display": "Office outpatient visit, established patient"
                }
              ],
              "text": "Office outpatient visit, established patient"
            },
            "encounter": [
              {
                "reference": "urn:uuid:f250b1ef-cb67-5d8b-b2db-e7fa797a2978"
              }
            ],
            "unitPrice": {
              "value": 165.0,
              "currency": "USD"
            },
            "net": {
              "value": 165.0,
              "currency": "USD"
            }
          }
        ],
        "total": {
          "value": 165.0,
          "currency": "USD"
        }
      },
      "request": {
        "method": "POST",
        "url": "Claim"
      }
    },
    {
      "fullUrl": "urn:uuid:addd342f-c204-5db7-a52d-9e2575d2a341",
      "resource": {
        "resourceType": "ExplanationOfBenefit",
        "id": "02b19ea6-74fa-579b-98cc-65d840755aab",
        "meta": {
          "tag": [
            {
              "system": "http://terminology.hl7.org/CodeSystem/v3-ActReason",
              "code": "HTEST",
              "display": "test health data"
            }
          ]
        },
        "identifier": [
          {
            "system": "https://parkerapex.com/atlas/explanation-of-benefit",
            "value": "02b19ea6-74fa-579b-98cc-65d840755aab"
          }
        ],
        "status": "active",
        "type": {
          "coding": [
            {
              "system": "http://terminology.hl7.org/CodeSystem/claim-type",
              "code": "professional",
              "display": "Professional"
            }
          ]
        },
        "use": "claim",
        "patient": {
          "reference": "urn:uuid:57e6cb1e-9930-5520-8c92-845afe5b38e3"
        },
        "created": "2026-06-21",
        "insurer": {
          "reference": "urn:uuid:54d8412e-f425-5f79-9fde-fee6dbf75edb"
        },
        "provider": {
          "reference": "urn:uuid:22edec61-448d-5da6-bc14-2da33c158817"
        },
        "outcome": "complete",
        "claim": {
          "reference": "urn:uuid:9cc489c7-04b5-5522-8adb-db0b0a853152"
        },
        "insurance": [
          {
            "focal": true,
            "coverage": {
              "reference": "urn:uuid:6d2604b0-8843-5267-929c-a7862e614169"
            }
          }
        ],
        "item": [
          {
            "sequence": 1,
            "productOrService": {
              "coding": [
                {
                  "system": "http://www.ama-assn.org/go/cpt",
                  "code": "99213",
                  "display": "Office outpatient visit, established patient"
                }
              ],
              "text": "Office outpatient visit, established patient"
            },
            "encounter": [
              {
                "reference": "urn:uuid:f250b1ef-cb67-5d8b-b2db-e7fa797a2978"
              }
            ],
            "adjudication": [
              {
                "category": {
                  "coding": [
                    {
                      "code": "submitted"
                    }
                  ]
                },
                "amount": {
                  "value": 165.0,
                  "currency": "USD"
                }
              },
              {
                "category": {
                  "coding": [
                    {
                      "code": "eligible"
                    }
                  ]
                },
                "amount": {
                  "value": 125.4,
                  "currency": "USD"
                }
              },
              {
                "category": {
                  "coding": [
                    {
                      "code": "benefit"
                    }
                  ]
                },
                "amount": {
                  "value": 100.32,
                  "currency": "USD"
                }
              },
              {
                "category": {
                  "coding": [
                    {
                      "code": "copay"
                    }
                  ]
                },
                "amount": {
                  "value": 25.08,
                  "currency": "USD"
                }
              }
            ]
          }
        ],
        "total": [
          {
            "category": {
              "coding": [
                {
                  "code": "submitted"
                }
              ]
            },
            "amount": {
              "value": 165.0,
              "currency": "USD"
            }
          },
          {
            "category": {
              "coding": [
                {
                  "code": "benefit"
                }
              ]
            },
            "amount": {
              "value": 100.32,
              "currency": "USD"
            }
          }
        ]
      },
      "request": {
        "method": "POST",
        "url": "ExplanationOfBenefit"
      }
    },
    {
      "fullUrl": "urn:uuid:64391b4a-329d-57c4-8b56-d1953160c92b",
      "resource": {
        "resourceType": "MeasureReport",
        "id": "d0c098b5-e7f9-5e51-8c4d-19597578926f",
        "meta": {
          "profile": [
            "http://hl7.org/fhir/us/davinci-deqm/StructureDefinition/indv-measurereport-deqm"
          ],
          "tag": [
            {
              "system": "http://terminology.hl7.org/CodeSystem/v3-ActReason",
              "code": "HTEST",
              "display": "test health data"
            }
          ]
        },
        "status": "complete",
        "type": "individual",
        "measure": "https://parkerapex.com/fhir/Measure/DM-HbA1c",
        "subject": {
          "reference": "urn:uuid:57e6cb1e-9930-5520-8c92-845afe5b38e3"
        },
        "date": "2026-12-31",
        "period": {
          "start": "2026-01-01",
          "end": "2026-12-31"
        },
        "group": [
          {
            "population": [
              {
                "code": {
                  "coding": [
                    {
                      "system": "http://terminology.hl7.org/CodeSystem/measure-population",
                      "code": "initial-population",
                      "display": "Initial Population"
                    }
                  ]
                },
                "count": 0
              },
              {
                "code": {
                  "coding": [
                    {
                      "system": "http://terminology.hl7.org/CodeSystem/measure-population",
                      "code": "denominator",
                      "display": "Denominator"
                    }
                  ]
                },
                "count": 0
              },
              {
                "code": {
                  "coding": [
                    {
                      "system": "http://terminology.hl7.org/CodeSystem/measure-population",
                      "code": "numerator",
                      "display": "Numerator"
                    }
                  ]
                },
                "count": 0
              }
            ]
          }
        ]
      },
      "request": {
        "method": "POST",
        "url": "MeasureReport"
      }
    },
    {
      "fullUrl": "urn:uuid:88d45d3f-5727-5e6c-8230-ff82d29b888f",
      "resource": {
        "resourceType": "MeasureReport",
        "id": "e843fae1-5238-51db-bce1-cf926333e782",
        "meta": {
          "profile": [
            "http://hl7.org/fhir/us/davinci-deqm/StructureDefinition/indv-measurereport-deqm"
          ],
          "tag": [
            {
              "system": "http://terminology.hl7.org/CodeSystem/v3-ActReason",
              "code": "HTEST",
              "display": "test health data"
            }
          ]
        },
        "status": "complete",
        "type": "individual",
        "measure": "https://parkerapex.com/fhir/Measure/HTN-BPControl",
        "subject": {
          "reference": "urn:uuid:57e6cb1e-9930-5520-8c92-845afe5b38e3"
        },
        "date": "2026-12-31",
        "period": {
          "start": "2026-01-01",
          "end": "2026-12-31"
        },
        "group": [
          {
            "population": [
              {
                "code": {
                  "coding": [
                    {
                      "system": "http://terminology.hl7.org/CodeSystem/measure-population",
                      "code": "initial-population",
                      "display": "Initial Population"
                    }
                  ]
                },
                "count": 1
              },
              {
                "code": {
                  "coding": [
                    {
                      "system": "http://terminology.hl7.org/CodeSystem/measure-population",
                      "code": "denominator",
                      "display": "Denominator"
                    }
                  ]
                },
                "count": 1
              },
              {
                "code": {
                  "coding": [
                    {
                      "system": "http://terminology.hl7.org/CodeSystem/measure-population",
                      "code": "numerator",
                      "display": "Numerator"
                    }
                  ]
                },
                "count": 0
              }
            ],
            "measureScore": {
              "value": 0.0,
              "unit": "1"
            }
          }
        ]
      },
      "request": {
        "method": "POST",
        "url": "MeasureReport"
      }
    },
    {
      "fullUrl": "urn:uuid:5d8f1250-897e-580d-9e4a-5c0d4f831d9a",
      "resource": {
        "resourceType": "MeasureReport",
        "id": "f80fe7b7-892b-53a4-8dfa-2bd7fab47ee6",
        "meta": {
          "profile": [
            "http://hl7.org/fhir/us/davinci-deqm/StructureDefinition/indv-measurereport-deqm"
          ],
          "tag": [
            {
              "system": "http://terminology.hl7.org/CodeSystem/v3-ActReason",
              "code": "HTEST",
              "display": "test health data"
            }
          ]
        },
        "status": "complete",
        "type": "individual",
        "measure": "https://parkerapex.com/fhir/Measure/PreventiveCare",
        "subject": {
          "reference": "urn:uuid:57e6cb1e-9930-5520-8c92-845afe5b38e3"
        },
        "date": "2026-12-31",
        "period": {
          "start": "2026-01-01",
          "end": "2026-12-31"
        },
        "group": [
          {
            "population": [
              {
                "code": {
                  "coding": [
                    {
                      "system": "http://terminology.hl7.org/CodeSystem/measure-population",
                      "code": "initial-population",
                      "display": "Initial Population"
                    }
                  ]
                },
                "count": 1
              },
              {
                "code": {
                  "coding": [
                    {
                      "system": "http://terminology.hl7.org/CodeSystem/measure-population",
                      "code": "denominator",
                      "display": "Denominator"
                    }
                  ]
                },
                "count": 1
              },
              {
                "code": {
                  "coding": [
                    {
                      "system": "http://terminology.hl7.org/CodeSystem/measure-population",
                      "code": "numerator",
                      "display": "Numerator"
                    }
                  ]
                },
                "count": 1
              }
            ],
            "measureScore": {
              "value": 1.0,
              "unit": "1"
            }
          }
        ]
      },
      "request": {
        "method": "POST",
        "url": "MeasureReport"
      }
    },
    {
      "fullUrl": "urn:uuid:54cf6e1b-e700-5e64-bc47-d5fddf6b16a5",
      "resource": {
        "resourceType": "MeasureReport",
        "id": "0e71876b-2b9f-57a5-b314-d8807d27bbd4",
        "meta": {
          "profile": [
            "http://hl7.org/fhir/us/davinci-deqm/StructureDefinition/indv-measurereport-deqm"
          ],
          "tag": [
            {
              "system": "http://terminology.hl7.org/CodeSystem/v3-ActReason",
              "code": "HTEST",
              "display": "test health data"
            }
          ]
        },
        "status": "complete",
        "type": "individual",
        "measure": "https://parkerapex.com/fhir/Measure/FluVaccine",
        "subject": {
          "reference": "urn:uuid:57e6cb1e-9930-5520-8c92-845afe5b38e3"
        },
        "date": "2026-12-31",
        "period": {
          "start": "2026-01-01",
          "end": "2026-12-31"
        },
        "group": [
          {
            "population": [
              {
                "code": {
                  "coding": [
                    {
                      "system": "http://terminology.hl7.org/CodeSystem/measure-population",
                      "code": "initial-population",
                      "display": "Initial Population"
                    }
                  ]
                },
                "count": 1
              },
              {
                "code": {
                  "coding": [
                    {
                      "system": "http://terminology.hl7.org/CodeSystem/measure-population",
                      "code": "denominator",
                      "display": "Denominator"
                    }
                  ]
                },
                "count": 1
              },
              {
                "code": {
                  "coding": [
                    {
                      "system": "http://terminology.hl7.org/CodeSystem/measure-population",
                      "code": "numerator",
                      "display": "Numerator"
                    }
                  ]
                },
                "count": 0
              }
            ],
            "measureScore": {
              "value": 0.0,
              "unit": "1"
            }
          }
        ]
      },
      "request": {
        "method": "POST",
        "url": "MeasureReport"
      }
    },
    {
      "fullUrl": "urn:uuid:3c34812d-74e3-58d1-b0da-f274601b8a23",
      "resource": {
        "resourceType": "MeasureReport",
        "id": "9812ec5d-d293-5462-985b-b32bf05f2e9c",
        "meta": {
          "profile": [
            "http://hl7.org/fhir/us/davinci-deqm/StructureDefinition/indv-measurereport-deqm"
          ],
          "tag": [
            {
              "system": "http://terminology.hl7.org/CodeSystem/v3-ActReason",
              "code": "HTEST",
              "display": "test health data"
            }
          ]
        },
        "status": "complete",
        "type": "individual",
        "measure": "https://parkerapex.com/fhir/Measure/PedWellChild",
        "subject": {
          "reference": "urn:uuid:57e6cb1e-9930-5520-8c92-845afe5b38e3"
        },
        "date": "2026-12-31",
        "period": {
          "start": "2026-01-01",
          "end": "2026-12-31"
        },
        "group": [
          {
            "population": [
              {
                "code": {
                  "coding": [
                    {
                      "system": "http://terminology.hl7.org/CodeSystem/measure-population",
                      "code": "initial-population",
                      "display": "Initial Population"
                    }
                  ]
                },
                "count": 0
              },
              {
                "code": {
                  "coding": [
                    {
                      "system": "http://terminology.hl7.org/CodeSystem/measure-population",
                      "code": "denominator",
                      "display": "Denominator"
                    }
                  ]
                },
                "count": 0
              },
              {
                "code": {
                  "coding": [
                    {
                      "system": "http://terminology.hl7.org/CodeSystem/measure-population",
                      "code": "numerator",
                      "display": "Numerator"
                    }
                  ]
                },
                "count": 0
              }
            ]
          }
        ]
      },
      "request": {
        "method": "POST",
        "url": "MeasureReport"
      }
    }
  ]
}